<Properties StartupConfiguration="{60140119-B5CC-44CD-88B1-77DFCEFEDB95}|Default">
  <MonoDevelop.Ide.Workbench ActiveDocument="WebApplication2/Views/FleetManagement/Edit.cshtml">
    <Files>
      <File FileName="WebApplication2/Controllers/FleetManagementController.cs" Line="109" Column="145" IsPinned="True" />
      <File FileName="WebApplication2/Views/FleetManagement/Index.cshtml" Line="11" Column="68" />
      <File FileName="WebApplication2/Views/FleetManagement/AddVehicle.cshtml" Line="25" Column="5" />
      <File FileName="WebApplication2/Controllers/HomeController.cs" Line="49" Column="13" />
      <File FileName="WebApplication2/Views/FleetManagement/Edit.cshtml" Line="15" Column="33" />
    </Files>
    <Pads>
      <Pad Id="ProjectPad">
        <State name="__root__">
          <Node name="UniDelWebApplication" expanded="True">
            <Node name="UniDelWebApplication" expanded="True">
              <Node name="Controllers" expanded="True" />
              <Node name="Models" expanded="True" />
              <Node name="Views" expanded="True">
                <Node name="FleetManagement" expanded="True">
                  <Node name="Edit.cshtml" selected="True" />
                </Node>
              </Node>
              <Node name="wwwroot" expanded="True" />
            </Node>
          </Node>
        </State>
      </Pad>
    </Pads>
  </MonoDevelop.Ide.Workbench>
  <MonoDevelop.Ide.ItemProperties.UniDelWebApplication PreferredExecutionTarget="/Applications/Google Chrome.app" />
  <MonoDevelop.Ide.DebuggingService.PinnedWatches />
  <MonoDevelop.Ide.Workspace ActiveConfiguration="Debug" />
  <MonoDevelop.Ide.DebuggingService.Breakpoints>
    <BreakpointStore />
  </MonoDevelop.Ide.DebuggingService.Breakpoints>
  <MultiItemStartupConfigurations />
</Properties>